cli_lm/__init__.py
cli_lm/helpers.py
cli_lm/main.py
cli_lm-0.1.6.dist-info/licenses/LICENSE
cli_lm-0.1.6.dist-info/METADATA
cli_lm-0.1.6.dist-info/WHEEL
cli_lm-0.1.6.dist-info/entry_points.txt
cli_lm-0.1.6.dist-info/top_level.txt
cli_lm-0.1.6.dist-info/RECORD
