Metadata-Version: 2.4
Name: cli-lm
Version: 0.1.6
Summary: A CLI tool for prompting an LLM
Author-email: Ian Davenport <davenport.ianc@gmail.com>
License: MIT
Project-URL: Homepage, https://github.com/davenpi/cli_lm
Project-URL: Bug Tracker, https://github.com/davenpi/cli_lm/issues
Project-URL: Documentation, https://github.com/davenpi/cli_lm#readme
Requires-Python: >=3.12
License-File: LICENSE
Requires-Dist: openai>=1.71.0
Dynamic: license-file
